{
  "applicable": false,
  "rate": {
    "currency": {
      "meta": {
        "href": "https://online.moysklad.ru/api/remap/1.1/entity/currency/baac25f0-50ac-11e5-300d-c79b00000055",
        "metadataHref": "https://online.moysklad.ru/api/remap/1.1/entity/currency/metadata",
        "type": "currency",
        "mediaType": "application/json"
      }
    }
  },
  "sum": 0,
  "organization": {
    "meta": {
      "href": "https://online.moysklad.ru/api/remap/1.1/entity/counterparty/1485d676-32ca-11e6-8a84-bae500000009",
      "metadataHref": "https://online.moysklad.ru/api/remap/1.1/entity/counterparty/metadata",
      "type": "counterparty",
      "mediaType": "application/json"
    }
  },
  "store": {
    "meta": {
      "href": "https://online.moysklad.ru/api/remap/1.1/entity/store/faf3ff5b-2e58-11e6-8a84-bae500000050",
      "metadataHref": "https://online.moysklad.ru/api/remap/1.1/entity/store/metadata",
      "type": "store",
      "mediaType": "application/json"
    }
  },
  "agent": {
    "meta": {
      "href": "https://online.moysklad.ru/api/remap/1.1/entity/organization/fae3561a-2e58-11e6-8a84-bae50000004e",
      "metadataHref": "https://online.moysklad.ru/api/remap/1.1/entity/organization/metadata",
      "type": "organization",
      "mediaType": "application/json"
    }
  },
  "organizationAccount": {
    "meta": {
      "href": "https://online.moysklad.ru/api/remap/1.1/entity/organization/fae3561a-2e58-11e6-8a84-bae50000004e/accounts/fae39d66-2e58-11e6-8a84-bae50000004f",
      "type": "account",
      "mediaType": "application/json"
    }
  },
  "agentAccount": {
    "meta": {
      "href": "https://online.moysklad.ru/api/remap/1.1/entity/counterparty/1485d676-32ca-11e6-8a84-bae500000009/accounts/1485e43e-32ca-11e6-8a84-bae50000000a",
      "type": "account",
      "mediaType": "application/json"
    }
  },
  "created": "2007-02-07 17:16:41",
  "positions": {
    "meta": {
      "href": "https://online.moysklad.ru/api/remap/1.1",
      "type": "purchasereturnposition",
      "mediaType": "application/json",
      "size": 0,
      "limit": 100,
      "offset": 0
    },
    "rows": []
  },
  "vatEnabled": true,
  "vatIncluded": true,
  "supply": {
    "meta": {
      "href": "https://online.moysklad.ru/api/remap/1.1/entity/supply/373d2925-4a98-11e6-8a84-bae500000069",
      "metadataHref": "https://online.moysklad.ru/api/remap/1.1/entity/supply/metadata",
      "type": "supply",
      "mediaType": "application/json"
    }
  },
  "payedSum": 0
}
